dagster_stitch/__init__.py
dagster_stitch/asset_defs.py
dagster_stitch/ops.py
dagster_stitch/resources.py
dagster_stitch/types.py
dagster_stitch/utils.py
dagster_stitch/version.py
dagster_stitch-0.1.3.dist-info/LICENSE
dagster_stitch-0.1.3.dist-info/METADATA
dagster_stitch-0.1.3.dist-info/WHEEL
dagster_stitch-0.1.3.dist-info/top_level.txt
dagster_stitch-0.1.3.dist-info/RECORD
