Metadata-Version: 2.1
Name: dagster-stitch
Version: 0.1.3
Author-email: Mark Snidal <mark.snidal@gmail.com>
License: Apache-2.0
Requires-Python: >=3.7
License-File: LICENSE
Requires-Dist: dagster (~=1.1.19)
Requires-Dist: parse (~=1.19.0)
Provides-Extra: lint
Requires-Dist: black (~=22.12.0) ; extra == 'lint'
Provides-Extra: test
Requires-Dist: pytest (~=7.2.1) ; extra == 'test'
Requires-Dist: responses (~=0.22.0) ; extra == 'test'
